cdk_iot_core_certificates_v3/__init__.py
cdk_iot_core_certificates_v3/py.typed
cdk_iot_core_certificates_v3/_jsii/__init__.py
cdk_iot_core_certificates_v3/_jsii/cdk-iot-core-certificates-v3@0.1.0.jsii.tgz
cdk_iot_core_certificates_v3-0.1.0.dist-info/LICENSE
cdk_iot_core_certificates_v3-0.1.0.dist-info/METADATA
cdk_iot_core_certificates_v3-0.1.0.dist-info/WHEEL
cdk_iot_core_certificates_v3-0.1.0.dist-info/top_level.txt
cdk_iot_core_certificates_v3-0.1.0.dist-info/RECORD
